tstrait/__init__.py
tstrait/base.py
tstrait/genetic_value.py
tstrait/provenance.py
tstrait/simulate_effect_size.py
tstrait/simulate_environment.py
tstrait/simulate_phenotype.py
tstrait/trait_model.py
tstrait/.vs/slnx.sqlite
tstrait-0.1.1.dist-info/licenses/LICENSE
tstrait-0.1.1.dist-info/METADATA
tstrait-0.1.1.dist-info/WHEEL
tstrait-0.1.1.dist-info/top_level.txt
tstrait-0.1.1.dist-info/RECORD
