Metadata-Version: 2.4
Name: tstrait
Version: 0.1.1
Summary: Quantitative trait simulation of tree sequence data
Author: Daiki Tagami et al.
Maintainer-email: Tskit Developers <admin@tskit.dev>
License: MIT
Project-URL: Homepage, https://tskit.dev/tstrait/
Project-URL: Bug Tracker, https://github.com/tskit-dev/tstrait/issues
Project-URL: Documentation, https://tskit.dev/tstrait/docs/
Project-URL: Source Code, https://github.com/tskit-dev/tstrait
Keywords: gwas,population genetics,quantitative trait,simulation,statistical genetics,tree sequence,tskit
Classifier: Development Status :: 5 - Production/Stable
Classifier: Intended Audience :: Science/Research
Classifier: Intended Audience :: Developers
Classifier: License :: OSI Approved :: MIT License
Classifier: Programming Language :: Python
Classifier: Programming Language :: Python :: 3
Classifier: Programming Language :: Python :: 3.10
Classifier: Programming Language :: Python :: 3.11
Classifier: Programming Language :: Python :: 3.12
Classifier: Programming Language :: Python :: 3.13
Classifier: Programming Language :: Python :: 3 :: Only
Classifier: Topic :: Scientific/Engineering
Classifier: Topic :: Scientific/Engineering :: Bio-Informatics
Classifier: Operating System :: Microsoft :: Windows
Classifier: Operating System :: POSIX
Classifier: Operating System :: MacOS
Requires-Python: >=3.10
License-File: LICENSE
Requires-Dist: numpy>=1.20.3
Requires-Dist: numba>=0.57.0
Requires-Dist: pandas>=1.0
Requires-Dist: tskit>=0.5.5
Provides-Extra: test
Requires-Dist: msprime==1.3.4; extra == "test"
Requires-Dist: numba==0.61.2; extra == "test"
Requires-Dist: pandas==2.3.2; extra == "test"
Requires-Dist: tskit==0.6.4; extra == "test"
Requires-Dist: pytest==8.4.2; extra == "test"
Requires-Dist: pytest-cov==6.3.0; extra == "test"
Requires-Dist: pytest-xdist==3.8.0; extra == "test"
Requires-Dist: scipy==1.15.3; extra == "test"
Provides-Extra: docs
Requires-Dist: jupyter-book==1.0.4.post1; extra == "docs"
Requires-Dist: matplotlib==3.10.6; extra == "docs"
Requires-Dist: msprime==1.3.4; extra == "docs"
Requires-Dist: numba==0.61.2; extra == "docs"
Requires-Dist: numpydoc==1.9.0; extra == "docs"
Requires-Dist: pandas==2.3.2; extra == "docs"
Requires-Dist: sphinx-issues==5.0.1; extra == "docs"
Requires-Dist: tskit==0.6.4; extra == "docs"
Provides-Extra: dev
Requires-Dist: jupyter-book; extra == "dev"
Requires-Dist: matplotlib; extra == "dev"
Requires-Dist: msprime; extra == "dev"
Requires-Dist: numba; extra == "dev"
Requires-Dist: numpy; extra == "dev"
Requires-Dist: numpydoc; extra == "dev"
Requires-Dist: pandas; extra == "dev"
Requires-Dist: pre-commit; extra == "dev"
Requires-Dist: pytest; extra == "dev"
Requires-Dist: scipy; extra == "dev"
Requires-Dist: sphinx; extra == "dev"
Requires-Dist: sphinx-issues; extra == "dev"
Requires-Dist: tskit; extra == "dev"
Requires-Dist: pytest-cov; extra == "dev"
Requires-Dist: pytest-xdist; extra == "dev"
Provides-Extra: verification
Requires-Dist: matplotlib; extra == "verification"
Requires-Dist: numpy; extra == "verification"
Requires-Dist: pandas; extra == "verification"
Requires-Dist: scipy; extra == "verification"
Requires-Dist: statsmodels; extra == "verification"
Requires-Dist: seaborn; extra == "verification"
Requires-Dist: tqdm; extra == "verification"
Requires-Dist: argparse; extra == "verification"
Requires-Dist: daiquiri; extra == "verification"
Requires-Dist: msprime; extra == "verification"
Dynamic: license-file
